{"cube":{"dimensions":["year","month","direction","icao","country","zone","range"],"fields":["flights","paxs"]},"table":{"header":["year","month","direction","icao","country","zone","range","flights","paxs"],"rows":[[1998,1,"D","LFPO","FR","M","CC",64,881],[1998,1,"A","LFPO","FR","M","CC",62,832],[1998,2,"D","LFPO","FR","M","CC",55,772],[1998,2,"A","LFPO","FR","M","CC",56,786],[1998,3,"D","LFPO","FR","M","CC",69,1100],[1998,3,"A","LFPO","FR","M","CC",67,1009],[1998,4,"D","LFPO","FR","M","CC",63,1048],[1998,4,"A","LFPO","FR","M","CC",62,1070],[1998,5,"D","LFPO","FR","M","CC",49,747],[1998,5,"A","LFPO","FR","M","CC",50,795],[1998,6,"D","LFPO","FR","M","CC",63,1250],[1998,6,"A","LFPO","FR","M","CC",62,1308],[1998,7,"D","LFPO","FR","M","CC",51,702],[1998,7,"A","LFPO","FR","M","CC",50,722],[1998,9,"D","LFPO","FR","M","CC",65,973],[1998,9,"A","LFPO","FR","M","CC",61,782],[1998,10,"D","LFPO","FR","M","CC",66,960],[1998,10,"A","LFPO","FR","M","CC",64,959],[1998,11,"D","LFPO","FR","M","CC",56,914],[1998,11,"A","LFPO","FR","M","CC",53,818],[1998,12,"D","LFPO","FR","M","CC",52,711],[1998,12,"A","LFPO","FR","M","CC",58,843]]}}
