{"cube":{"dimensions":["year","month","direction","icao","country","zone","range"],"fields":["flights","paxs"]},"table":{"header":["year","month","direction","icao","country","zone","range","flights","paxs"],"rows":[[2003,5,"D","LFLC","FR","M","CC",32,528],[2003,6,"D","LFLC","FR","M","CC",40,860],[2003,6,"A","LFLC","FR","M","CC",40,782],[2003,7,"A","LFBH","FR","M","CC",22,564],[2003,7,"D","LFBH","FR","M","CC",22,624],[2003,7,"D","LFLC","FR","M","CC",46,979],[2003,7,"A","LFLC","FR","M","CC",48,1035],[2003,9,"D","LFLC","FR","M","CC",46,958],[2003,9,"A","LFLC","FR","M","CC",46,914],[2003,10,"D","LFLC","FR","M","CC",46,737],[2003,10,"A","LFLC","FR","M","CC",47,723]]}}
