{"cube":{"dimensions":["year","month","direction","icao","country","zone","range"],"fields":["flights","paxs"]},"table":{"header":["year","month","direction","icao","country","zone","range","flights","paxs"],"rows":[[1994,1,"D","LFPO","FR","M","CC",42,1345],[1994,1,"A","LFPO","FR","M","CC",42,1289],[1994,2,"D","LFPO","FR","M","CC",39,1206],[1994,2,"A","LFPO","FR","M","CC",37,1264],[1994,3,"D","LFPO","FR","M","CC",43,1467],[1994,3,"A","LFPO","FR","M","CC",45,1613],[1994,4,"D","LFPO","FR","M","CC",39,1392],[1994,4,"A","LFPO","FR","M","CC",41,1562],[1994,5,"D","LFPO","FR","M","CC",35,1285],[1994,5,"A","LFPO","FR","M","CC",38,1383],[1994,6,"D","LFPO","FR","M","CC",44,1832],[1994,6,"A","LFPO","FR","M","CC",45,1941],[1994,7,"D","LFPO","FR","M","CC",36,1274],[1994,7,"A","LFPO","FR","M","CC",38,1453],[1994,8,"D","LFPO","FR","M","CC",25,783],[1994,8,"A","LFPO","FR","M","CC",25,669],[1994,9,"D","LFPO","FR","M","CC",43,1557],[1994,9,"A","LFPO","FR","M","CC",45,1613],[1994,10,"D","LFPO","FR","M","CC",39,1445],[1994,10,"A","LFPO","FR","M","CC",40,1607],[1994,11,"D","LFPO","FR","M","CC",39,1474],[1994,11,"A","LFPO","FR","M","CC",41,1560],[1994,12,"D","LFPO","FR","M","CC",42,1385],[1994,12,"A","LFPO","FR","M","CC",38,1293]]}}
