{"cube":{"dimensions":["year","month","direction","icao","country","zone","range"],"fields":["flights","paxs"]},"table":{"header":["year","month","direction","icao","country","zone","range","flights","paxs"],"rows":[[1998,1,"D","LFPO","FR","M","CC",45,2374],[1998,1,"A","LFPO","FR","M","CC",46,2571],[1998,2,"D","LFBD","FR","M","CC",40,505],[1998,2,"D","LFPO","FR","M","CC",48,2420],[1998,2,"A","LFPO","FR","M","CC",46,2671],[1998,3,"D","LFPO","FR","M","CC",58,3018],[1998,3,"D","LFRS","FR","M","CC",44,525],[1998,3,"A","LFPO","FR","M","CC",59,3156],[1998,4,"D","LFPO","FR","M","CC",63,2898],[1998,4,"A","LFPO","FR","M","CC",62,3073],[1998,5,"A","EGSS","GB","I","MC",23,1029],[1998,5,"D","EGSS","GB","I","MC",23,1269],[1998,5,"D","LFPO","FR","M","CC",51,2435],[1998,5,"A","LFPO","FR","M","CC",50,2602],[1998,6,"A","EGSS","GB","I","MC",54,3529],[1998,6,"A","LFBD","FR","M","CC",45,739],[1998,6,"A","LFBO","FR","M","CC",43,564],[1998,6,"D","EGSS","GB","I","MC",54,3387],[1998,6,"D","LFBD","FR","M","CC",45,788],[1998,6,"D","LFBO","FR","M","CC",43,565],[1998,6,"D","LFPG","FR","M","CC",5,560],[1998,6,"D","LFPO","FR","M","CC",67,2930],[1998,6,"D","LFQQ","FR","M","CC",43,648],[1998,6,"D","LFRS","FR","M","CC",43,662],[1998,6,"A","LFPO","FR","M","CC",65,3020],[1998,6,"A","LFQQ","FR","M","CC",44,643],[1998,6,"A","LFRS","FR","M","CC",41,589],[1998,7,"A","EGSS","GB","I","MC",58,3340],[1998,7,"D","EGSS","GB","I","MC",60,3794],[1998,7,"D","LFPO","FR","M","CC",65,2646],[1998,7,"D","LFRS","FR","M","CC",42,510],[1998,7,"A","LFPO","FR","M","CC",64,2872],[1998,8,"A","EGSS","GB","I","MC",58,4067],[1998,8,"D","EGSS","GB","I","MC",58,3904],[1998,8,"D","LFPO","FR","M","CC",17,509],[1998,9,"A","EGSS","GB","I","MC",39,2365],[1998,9,"D","EGSS","GB","I","MC",39,3275],[1998,9,"D","LFPO","FR","M","CC",62,2781],[1998,9,"D","LFRS","FR","M","CC",44,512],[1998,9,"A","LFPO","FR","M","CC",63,3129],[1998,9,"A","LFRS","FR","M","CC",45,501],[1998,10,"A","EGSS","GB","I","MC",30,2247],[1998,10,"D","EGSS","GB","I","MC",30,2359],[1998,10,"D","LFPO","FR","M","CC",65,3168],[1998,10,"D","LFRS","FR","M","CC",44,553],[1998,10,"A","LFPO","FR","M","CC",65,3340],[1998,11,"A","EGSS","GB","I","MC",30,1627],[1998,11,"D","EGSS","GB","I","MC",30,1636],[1998,11,"D","LFPO","FR","M","CC",57,2887],[1998,11,"A","LFPO","FR","M","CC",58,3050],[1998,12,"A","EGSS","GB","I","MC",30,2133],[1998,12,"D","EGSS","GB","I","MC",30,1807],[1998,12,"D","LFPO","FR","M","CC",59,3103],[1998,12,"D","LFRS","FR","M","CC",43,504],[1998,12,"A","LFPO","FR","M","CC",59,3408]]}}
