{"cube":{"dimensions":["year","month","direction","icao","country","zone","range"],"fields":["flights","paxs"]},"table":{"header":["year","month","direction","icao","country","zone","range","flights","paxs"],"rows":[[2014,1,"A","EGSS","GB","I","MC",14,1834],[2014,1,"D","EGSS","GB","I","MC",15,2225],[2014,2,"A","EGSS","GB","I","MC",12,1772],[2014,2,"D","EGSS","GB","I","MC",12,1845],[2014,3,"A","EGSS","GB","I","MC",12,1860],[2014,3,"D","EGSS","GB","I","MC",12,1843],[2014,4,"A","EGNX","GB","I","MC",12,1592],[2014,4,"A","EGSS","GB","I","MC",26,3768],[2014,4,"D","EGNX","GB","I","MC",12,1618],[2014,4,"D","EGSS","GB","I","MC",25,3823],[2014,5,"A","EGNX","GB","I","MC",13,1957],[2014,5,"A","EGSS","GB","I","MC",27,4355],[2014,5,"D","EGNX","GB","I","MC",13,1763],[2014,5,"D","EGSS","GB","I","MC",27,4091],[2014,6,"A","EGNX","GB","I","MC",13,1785],[2014,6,"A","EGSS","GB","I","MC",25,3715],[2014,6,"D","EGNX","GB","I","MC",13,1888],[2014,6,"D","EGSS","GB","I","MC",25,3491],[2014,7,"A","EGNM","GB","I","MC",9,1373],[2014,7,"A","EGNX","GB","I","MC",13,2117],[2014,7,"A","EGSS","GB","I","MC",31,5216],[2014,7,"D","EGNM","GB","I","MC",9,1104],[2014,7,"D","EGNX","GB","I","MC",13,1925],[2014,7,"D","EGSS","GB","I","MC",31,4772],[2014,8,"A","EGNM","GB","I","MC",9,1380],[2014,8,"A","EGNX","GB","I","MC",14,2322],[2014,8,"A","EGSS","GB","I","MC",26,4559],[2014,8,"D","EGNM","GB","I","MC",8,1402],[2014,8,"D","EGNX","GB","I","MC",14,2412],[2014,8,"D","EGSS","GB","I","MC",26,4549],[2014,9,"A","EGNX","GB","I","MC",13,1794],[2014,9,"A","EGSS","GB","I","MC",22,2827],[2014,9,"D","EGNX","GB","I","MC",13,2025],[2014,9,"D","EGSS","GB","I","MC",22,3125],[2014,10,"A","EGNX","GB","I","MC",11,1419],[2014,10,"A","EGSS","GB","I","MC",27,3781],[2014,10,"D","EGNX","GB","I","MC",11,1546],[2014,10,"D","EGSS","GB","I","MC",27,3949],[2014,11,"A","EGSS","GB","I","MC",17,2289],[2014,11,"D","EGSS","GB","I","MC",17,2542],[2014,12,"A","EGSS","GB","I","MC",17,2565],[2014,12,"D","EGSS","GB","I","MC",17,2367]]}}
