{"cube":{"dimensions":["year","month","direction","icao","country","zone","range"],"fields":["flights","paxs"]},"table":{"header":["year","month","direction","icao","country","zone","range","flights","paxs"],"rows":[[2014,1,"A","LFLL","FR","M","CC",73,3045],[2014,1,"D","LFLL","FR","M","CC",73,3101],[2014,2,"A","LFLL","FR","M","CC",69,2987],[2014,2,"D","LFLL","FR","M","CC",70,2993],[2014,3,"A","LFLL","FR","M","CC",73,3355],[2014,3,"D","LFLL","FR","M","CC",73,3284],[2014,4,"A","GMMX","MA","I","MC",4,750],[2014,4,"A","LFLL","FR","M","CC",72,3570],[2014,4,"D","LFLL","FR","M","CC",72,3653],[2014,5,"A","GMMX","MA","I","MC",5,1000],[2014,5,"A","LFKJ","FR","M","CC",9,927],[2014,5,"A","LFLL","FR","M","CC",55,2920],[2014,5,"D","LFKJ","FR","M","CC",9,984],[2014,5,"D","LFLL","FR","M","CC",54,2973],[2014,6,"A","LFKJ","FR","M","CC",8,815],[2014,6,"A","LFLL","FR","M","CC",70,4151],[2014,6,"D","LFKJ","FR","M","CC",8,888],[2014,6,"D","LFLL","FR","M","CC",70,3984],[2014,7,"A","EGMC","GB","I","MC",19,701],[2014,7,"A","LFKJ","FR","M","CC",9,875],[2014,7,"A","LFLL","FR","M","CC",74,3961],[2014,7,"D","EGMC","GB","I","MC",20,736],[2014,7,"D","LFKJ","FR","M","CC",9,1035],[2014,7,"D","LFLL","FR","M","CC",74,3922],[2014,8,"A","EGMC","GB","I","MC",25,1076],[2014,8,"A","LFKJ","FR","M","CC",9,1030],[2014,8,"A","LFLL","FR","M","CC",51,2686],[2014,8,"D","EGMC","GB","I","MC",25,1026],[2014,8,"D","LFKJ","FR","M","CC",9,912],[2014,8,"D","LFLL","FR","M","CC",52,2661],[2014,9,"A","EGMC","GB","I","MC",17,506],[2014,9,"A","LFKJ","FR","M","CC",9,966],[2014,9,"A","LFLL","FR","M","CC",78,3686],[2014,9,"D","EGMC","GB","I","MC",17,577],[2014,9,"D","LFKJ","FR","M","CC",10,865],[2014,9,"D","LFLL","FR","M","CC",78,3798],[2014,10,"A","EGMC","GB","I","MC",17,563],[2014,10,"A","LFLL","FR","M","CC",81,4112],[2014,10,"D","EGMC","GB","I","MC",17,635],[2014,10,"D","LFLL","FR","M","CC",82,4125],[2014,11,"A","GMMX","MA","I","MC",5,920],[2014,11,"A","LFLL","FR","M","CC",68,3205],[2014,11,"D","LFLL","FR","M","CC",67,3224],[2014,11,"D","LFRC","FR","M","CC",5,750],[2014,12,"A","LFLL","FR","M","CC",68,3357],[2014,12,"D","LFLL","FR","M","CC",69,3313]]}}
