{"cube":{"dimensions":["year","month","direction","icao","country","zone","range"],"fields":["flights","paxs"]},"table":{"header":["year","month","direction","icao","country","zone","range","flights","paxs"],"rows":[[1997,1,"A","LFPO","FR","M","CC",227,15599],[1997,1,"A","LFRB","FR","M","CC",9,823],[1997,1,"D","LFPO","FR","M","CC",228,18185],[1997,1,"D","LFRB","FR","M","CC",9,855],[1997,2,"A","LFPO","FR","M","CC",227,19394],[1997,2,"A","LFRB","FR","M","CC",8,787],[1997,2,"D","LFPO","FR","M","CC",226,18779],[1997,2,"D","LFRB","FR","M","CC",7,622],[1997,3,"A","LFPG","FR","M","CC",5,934],[1997,3,"A","LFPO","FR","M","CC",247,20272],[1997,3,"A","LFRB","FR","M","CC",9,960],[1997,3,"D","LFPG","FR","M","CC",5,913],[1997,3,"D","LFPO","FR","M","CC",245,19684],[1997,3,"D","LFRB","FR","M","CC",8,800],[1997,4,"A","LFKB","FR","M","CC",42,501],[1997,4,"A","LFPO","FR","M","CC",213,23745],[1997,4,"A","LFRB","FR","M","CC",9,986],[1997,4,"D","LFPO","FR","M","CC",214,23736],[1997,4,"D","LFRB","FR","M","CC",7,752],[1997,5,"A","LFPO","FR","M","CC",236,23205],[1997,5,"A","LFRB","FR","M","CC",8,930],[1997,5,"D","LFPO","FR","M","CC",239,23622],[1997,5,"D","LFRB","FR","M","CC",8,889],[1997,6,"A","LFKB","FR","M","CC",52,533],[1997,6,"A","LFKJ","FR","M","CC",50,517],[1997,6,"A","LFLC","FR","M","CC",103,1220],[1997,6,"A","LFPO","FR","M","CC",257,28639],[1997,6,"A","LFRB","FR","M","CC",9,1136],[1997,6,"D","LFKB","FR","M","CC",44,501],[1997,6,"D","LFKJ","FR","M","CC",50,553],[1997,6,"D","LFLC","FR","M","CC",82,895],[1997,6,"D","LFPO","FR","M","CC",256,26931],[1997,6,"D","LFRB","FR","M","CC",4,517],[1997,7,"A","LFKB","FR","M","CC",62,614],[1997,7,"A","LFKJ","FR","M","CC",62,746],[1997,7,"A","LFLC","FR","M","CC",89,1594],[1997,7,"A","LFPO","FR","M","CC",275,32477],[1997,7,"A","LFRB","FR","M","CC",9,1137],[1997,7,"D","LEIB","ES","I","MC",7,706],[1997,7,"D","LFKB","FR","M","CC",58,791],[1997,7,"D","LFKJ","FR","M","CC",59,774],[1997,7,"D","LFLC","FR","M","CC",83,1529],[1997,7,"D","LFPO","FR","M","CC",276,28714],[1997,7,"D","LFRB","FR","M","CC",8,1005],[1997,8,"A","LEIB","ES","I","MC",6,583],[1997,8,"A","LFKB","FR","M","CC",64,1200],[1997,8,"A","LFKJ","FR","M","CC",63,1133],[1997,8,"A","LFLC","FR","M","CC",52,1288],[1997,8,"A","LFPO","FR","M","CC",271,28546],[1997,8,"A","LFRB","FR","M","CC",10,1255],[1997,8,"D","LEIB","ES","I","MC",5,544],[1997,8,"D","LFKB","FR","M","CC",61,1017],[1997,8,"D","LFKJ","FR","M","CC",65,931],[1997,8,"D","LFLC","FR","M","CC",53,1370],[1997,8,"D","LFPO","FR","M","CC",271,30959],[1997,8,"D","LFRB","FR","M","CC",10,1167],[1997,8,"D","LFRK","FR","M","CC",7,663],[1997,8,"D","LFST","FR","M","CC",18,591],[1997,9,"A","LFKB","FR","M","CC",45,523],[1997,9,"A","LFLC","FR","M","CC",96,1386],[1997,9,"A","LFPO","FR","M","CC",260,23633],[1997,9,"A","LFRB","FR","M","CC",8,950],[1997,9,"D","LFKJ","FR","M","CC",46,502],[1997,9,"D","LFLC","FR","M","CC",96,1432],[1997,9,"D","LFPO","FR","M","CC",260,27638],[1997,9,"D","LFRB","FR","M","CC",8,779],[1997,10,"A","LFLC","FR","M","CC",94,1074],[1997,10,"A","LFPO","FR","M","CC",276,22749],[1997,10,"A","LFRB","FR","M","CC",9,904],[1997,10,"D","LFLC","FR","M","CC",92,1101],[1997,10,"D","LFPO","FR","M","CC",277,23361],[1997,10,"D","LFRB","FR","M","CC",8,742],[1997,11,"A","LFLC","FR","M","CC",72,619],[1997,11,"A","LFPO","FR","M","CC",288,20036],[1997,11,"A","LFRB","FR","M","CC",9,952],[1997,11,"D","LFLC","FR","M","CC",74,676],[1997,11,"D","LFPO","FR","M","CC",287,21582],[1997,11,"D","LFRB","FR","M","CC",9,908],[1997,12,"A","LFLC","FR","M","CC",62,555],[1997,12,"A","LFPO","FR","M","CC",290,23532],[1997,12,"A","LFRB","FR","M","CC",9,902],[1997,12,"D","LFLC","FR","M","CC",62,550],[1997,12,"D","LFPO","FR","M","CC",287,21542],[1997,12,"D","LFRB","FR","M","CC",9,949]]}}
